{
  "enchantments": {
    "enabled": false,
    "list": [
      {
        "id": "set-bonus:resistance",
        "levels": 3,
        "power": {
          "base": 10,
          "increment": 20,
          "delta": 30
        },
        "toggleable": false,
        "effects": [{
          "id": "minecraft:resistance",
          "stacking": "ADDITIVE"
        }]
      }, {
        "id": "set-bonus:night-vision",
        "levels": 1,
        "power": {
          "base": 20,
          "delta": 20
        },
        "rarity": "COMMON",
        "slots": ["HEAD"],
        "target": "ARMOR_HEAD",
        "effects": [{
          "id": "minecraft:night_vision",
          "duration": 210
        }]
      }, {
        "enabled": false,
        "id": "set-bonus:speed",
        "levels": 3,
        "power": {
          "base": 20,
          "increment": 15,
          "delta": 20
        },
        "treasure": true,
        "rarity": "RARE",
        "target": "ARMOR_LEGS",
        "effects": [{
          "id": "minecraft:speed"
        }]
      }, {
        "id": "set-bonus:slow-fall",
        "levels": 1,
        "power": {
          "base": 20,
          "increment": 15,
          "delta": 20
        },
        "rarity": "RARE",
        "target": "ARMOR_FEET",
        "effects": [{
          "id": "minecraft:slow_falling"
        }]
      }, {
        "id": "set-bonus:jump-boost",
        "levels": 3,
        "power": {
          "base": 20,
          "increment": 15,
          "delta": 20
        },
        "treasure": true,
        "rarity": "RARE",
        "target": "ARMOR_FEET",
        "effects": [{
          "id": "minecraft:jump_boost"
        }]
      }, {
        "id": "set-bonus:netherite-haste",
        "levels": 1,
        "treasure": true,
        "rarity": "RARE",
        "target": "ARMOR_CHEST",
        "materials": ["NETHERITE"],
        "effects": [{
          "id": "minecraft:haste"
        }]
      }
    ]
  },
  "setBonuses": {
    "enabled": true,
    "list": [
      {
        "material": "GOLD",
        "partial": "OFF",
        "effects": [{
          "id": "minecraft:luck",
          "strength": 1
        },
        {
          "id": "extraalchemy:detection",
          "strength": 0
        }]
      },
      {
        "material": "CHAIN",
        "partial": "OFF",
        "effects": [{
          "id": "minecraft:speed",
          "strength": 0
        }]
      }, {
        "material": "LEATHER",
        "partial": "OFF",
        "toughness": 2.0,
        "effects": [{
          "id": "extraalchemy:detection",
          "strength": 0
        }]
      }
    ]
  }
}